dragon.py
dragon_pl-1.9.8.data/data/lib/site-packages/dragon.dll
dragon_pl-1.9.8.data/data/lib/site-packages/libdragon.dll
dragon_pl-1.9.8.dist-info/METADATA
dragon_pl-1.9.8.dist-info/WHEEL
dragon_pl-1.9.8.dist-info/top_level.txt
dragon_pl-1.9.8.dist-info/RECORD
